devpi_server/__init__.py
devpi_server/__main__.py
devpi_server/auth.py
devpi_server/auth_basic.py
devpi_server/auth_devpi.py
devpi_server/config.py
devpi_server/exceptions.py
devpi_server/filestore.py
devpi_server/filestore_fs.py
devpi_server/fileutil.py
devpi_server/fsck.py
devpi_server/genconfig.py
devpi_server/hookspecs.py
devpi_server/httpclient.py
devpi_server/importexport.py
devpi_server/init.py
devpi_server/interfaces.py
devpi_server/keyfs.py
devpi_server/keyfs_sqlite.py
devpi_server/keyfs_sqlite_fs.py
devpi_server/keyfs_types.py
devpi_server/log.py
devpi_server/main.py
devpi_server/markers.py
devpi_server/middleware.py
devpi_server/mirror.py
devpi_server/model.py
devpi_server/mythread.py
devpi_server/passwd.py
devpi_server/py.typed
devpi_server/readonly.py
devpi_server/replica.py
devpi_server/sizeof.py
devpi_server/view_auth.py
devpi_server/views.py
devpi_server/cfg/__init__.py
devpi_server/cfg/crontab.template
devpi_server/cfg/devpi.service.template
devpi_server/cfg/launchd-macos.txt.template
devpi_server/cfg/nginx-devpi-caching-http.conf.template
devpi_server/cfg/nginx-devpi-caching-location.conf.template
devpi_server/cfg/nginx-devpi-caching-proxy.conf.template
devpi_server/cfg/nginx-devpi-caching-server.conf.template
devpi_server/cfg/nginx-devpi.conf.template
devpi_server/cfg/supervisor-devpi.conf.template
devpi_server/cfg/supervisord.conf.template
devpi_server/cfg/windows-service.txt.template
devpi_server/vendor/__init__.py
devpi_server/vendor/_pip.py
devpi_server-6.17.0.dist-info/licenses/LICENSE
pytest_devpi_server/__init__.py
test_devpi_server/__init__.py
test_devpi_server/conftest.py
test_devpi_server/example.py
test_devpi_server/functional.py
test_devpi_server/plugin.py
test_devpi_server/py.typed
test_devpi_server/reqmock.py
test_devpi_server/simpypi.py
test_devpi_server/test_auth.py
test_devpi_server/test_authcheck.py
test_devpi_server/test_config.py
test_devpi_server/test_conftest.py
test_devpi_server/test_filestore.py
test_devpi_server/test_fileutil.py
test_devpi_server/test_fsck.py
devpi_server-6.17.0.dist-info/METADATA
devpi_server-6.17.0.dist-info/WHEEL
devpi_server-6.17.0.dist-info/entry_points.txt
devpi_server-6.17.0.dist-info/top_level.txt
devpi_server-6.17.0.dist-info/RECORD
