Metadata-Version: 2.4
Name: devpi-server
Version: 6.17.0
Summary: devpi-server: reliable, private, and pypi.org caching server
Maintainer-email: Florian Schulze <mail@pyfidelity.com>
License-Expression: MIT
Project-URL: Bug Tracker, https://github.com/devpi/devpi/issues
Project-URL: Changelog, https://github.com/devpi/devpi/blob/main/server/CHANGELOG
Project-URL: Documentation, https://doc.devpi.net
Project-URL: Funding, https://github.com/sponsors/devpi
Project-URL: Homepage, https://devpi.net
Project-URL: Source Code, https://github.com/devpi/devpi
Keywords: pypi,realtime,cache,server
Classifier: Development Status :: 5 - Production/Stable
Classifier: Environment :: Web Environment
Classifier: Intended Audience :: Developers
Classifier: Intended Audience :: System Administrators
Classifier: Programming Language :: Python
Classifier: Programming Language :: Python :: 3 :: Only
Classifier: Programming Language :: Python :: 3.9
Classifier: Programming Language :: Python :: 3.10
Classifier: Programming Language :: Python :: 3.11
Classifier: Programming Language :: Python :: 3.12
Classifier: Programming Language :: Python :: 3.13
Classifier: Programming Language :: Python :: Implementation :: PyPy
Classifier: Topic :: Internet :: WWW/HTTP :: WSGI :: Application
Classifier: Topic :: Internet :: WWW/HTTP
Requires-Python: >=3.9
License-File: LICENSE
Requires-Dist: argon2-cffi
Requires-Dist: attrs>=22.2.0
Requires-Dist: defusedxml
Requires-Dist: devpi_common<5,>3.6.0
Requires-Dist: httpx<1
Requires-Dist: itsdangerous>=0.24
Requires-Dist: lazy
Requires-Dist: legacy-cgi; python_version >= "3.13"
Requires-Dist: passlib[argon2]
Requires-Dist: platformdirs
Requires-Dist: pluggy<2.0,>=0.6.0
Requires-Dist: py>=1.4.23
Requires-Dist: pyramid>=2
Requires-Dist: repoze.lru>=0.6
Requires-Dist: strictyaml
Requires-Dist: waitress>=1.0.1
Requires-Dist: ruamel.yaml
Dynamic: license-file
